smart_notes_vault-1.0.0.dist-info/METADATA
smart_notes_vault-1.0.0.dist-info/WHEEL
snv/__init__.py
snv/classes.py
snv/io.py
snv/md.py
smart_notes_vault-1.0.0.dist-info/RECORD
