Metadata-Version: 2.1
Name: smart-notes-vault
Version: 1.0.0
Author-Email: Jan Kolomaznik <jan.kolomaznik@gmail.com>
License: MIT
Requires-Python: >=3.10
Requires-Dist: pyyaml>=6.0
